swarmauri_tool_gmail/GmailReadTool.py
swarmauri_tool_gmail/GmailSendTool.py
swarmauri_tool_gmail/__init__.py
swarmauri_tool_gmail-0.7.5.dist-info/LICENSE
swarmauri_tool_gmail-0.7.5.dist-info/METADATA
swarmauri_tool_gmail-0.7.5.dist-info/WHEEL
swarmauri_tool_gmail-0.7.5.dist-info/entry_points.txt
swarmauri_tool_gmail-0.7.5.dist-info/RECORD
